novlake/__init__.py
novlake/lake.py
novlake-0.1.0.dist-info/WHEEL
novlake-0.1.0.dist-info/METADATA
novlake-0.1.0.dist-info/RECORD
