Metadata-Version: 2.1
Name: novlake
Version: 0.1.0
Summary: Tools to work with our data lake
Author: Pierre-Marie Leveque
Author-email: pierre@noverde.com.br
Requires-Python: >=3.6,<4.0
Classifier: Programming Language :: Python :: 3
Classifier: Programming Language :: Python :: 3.6
Classifier: Programming Language :: Python :: 3.7
Requires-Dist: awswrangler (>=0.0.1,<0.0.2)
Requires-Dist: boto3 (>=1.9,<2.0)
Requires-Dist: python-dotenv (>=0.10.3,<0.11.0)
